odoo/addons/website_sale_product_style_badge/README.rst
odoo/addons/website_sale_product_style_badge/__init__.py
odoo/addons/website_sale_product_style_badge/__manifest__.py
odoo/addons/website_sale_product_style_badge/data/data.xml
odoo/addons/website_sale_product_style_badge/data/menus.xml
odoo/addons/website_sale_product_style_badge/i18n/ca.po
odoo/addons/website_sale_product_style_badge/i18n/es.po
odoo/addons/website_sale_product_style_badge/i18n/fr.po
odoo/addons/website_sale_product_style_badge/i18n/website_sale_product_style_badge.pot
odoo/addons/website_sale_product_style_badge/models/__init__.py
odoo/addons/website_sale_product_style_badge/models/product_style.py
odoo/addons/website_sale_product_style_badge/readme/CONFIGURE.rst
odoo/addons/website_sale_product_style_badge/readme/CONTRIBUTORS.rst
odoo/addons/website_sale_product_style_badge/readme/DESCRIPTION.rst
odoo/addons/website_sale_product_style_badge/readme/ROADMAP.rst
odoo/addons/website_sale_product_style_badge/readme/USAGE.rst
odoo/addons/website_sale_product_style_badge/security/ir.model.access.csv
odoo/addons/website_sale_product_style_badge/static/description/icon.png
odoo/addons/website_sale_product_style_badge/static/description/index.html
odoo/addons/website_sale_product_style_badge/static/src/scss/website_sale.scss
odoo/addons/website_sale_product_style_badge/templates/assets.xml
odoo/addons/website_sale_product_style_badge/templates/website_sale.xml
odoo/addons/website_sale_product_style_badge/views/product_style_views.xml
odoo/addons/website_sale_product_style_badge/views/product_template_views.xml
odoo13_addon_website_sale_product_style_badge-13.0.1.0.1.dev6.dist-info/METADATA
odoo13_addon_website_sale_product_style_badge-13.0.1.0.1.dev6.dist-info/WHEEL
odoo13_addon_website_sale_product_style_badge-13.0.1.0.1.dev6.dist-info/top_level.txt
odoo13_addon_website_sale_product_style_badge-13.0.1.0.1.dev6.dist-info/RECORD
